{
  "business_units": [
    {
      "unit_id": "trading-platform",
      "name": "Trading Platform",
      "criticality": "critical",
      "data_classification": "financial",
      "description": "Owns all real-time trading, fraud detection, and transaction analytics. PCI-DSS and SOX scope.",
      "owns_entity_patterns": [
        "apex-trading::func.src.trading.api.search_transactions",
        "apex-trading::func.src.trading.api.get_fraud_score",
        "apex-trading::func.src.trading.api.upload_trading_report",
        "apex-trading::func.src.trading.analytics.execute_raw_query",
        "apex-trading::func.src.trading.analytics.analyze_transaction",
        "apex-trading::func.src.trading.analytics.compute_risk_score"
      ]
    },
    {
      "unit_id": "payments-engineering",
      "name": "Payments Engineering",
      "criticality": "critical",
      "data_classification": "financial",
      "description": "Owns payment processing, card charging, and payment data APIs. PCI-DSS Level 1 scope.",
      "owns_entity_patterns": [
        "apex-payments::func.src.routes.ts.processPayment",
        "apex-payments::func.src.routes.ts.getPaymentStatus",
        "apex-payments::func.src.routes.ts.adminOverride",
        "apex-payments::func.src.routes.ts.chargeCard",
        "apex-payments::func.src.payment_processor.ts.executeRawPaymentQuery",
        "apex-payments::func.src.payment_processor.ts.chargeCard"
      ]
    },
    {
      "unit_id": "compliance-reporting",
      "name": "Compliance Reporting",
      "criticality": "high",
      "data_classification": "financial",
      "description": "Owns regulatory reporting and compliance data pipelines. SOX ITGC and PCI-DSS audit scope.",
      "owns_entity_patterns": [
        "apex-compliance::class.src.main.java.com.apex.compliance.controller.ReportController",
        "apex-compliance::class.src.main.java.com.apex.compliance.service.ReportService"
      ]
    },
    {
      "unit_id": "security-engineering",
      "name": "Security Engineering",
      "criticality": "high",
      "data_classification": "internal",
      "description": "Owns authentication middleware and input sanitization across all services.",
      "owns_entity_patterns": [
        "apex-payments::func.src.middleware.ts.sanitizePaymentInput",
        "apex-payments::func.src.middleware.ts.validateCardNumber",
        "apex-trading::func.src.trading.validators.sanitize_transaction_id",
        "apex-trading::func.src.trading.validators.sanitize_query_param"
      ]
    }
  ]
}
